README.txt
setup.cfg
setup.py
testingpackage12345/__init__.py
testingpackage12345/testpackge1.py
testingpackage12345.egg-info/PKG-INFO
testingpackage12345.egg-info/SOURCES.txt
testingpackage12345.egg-info/dependency_links.txt
testingpackage12345.egg-info/top_level.txt