Metadata-Version: 1.0
Name: testingpackage12345
Version: 0.4
Summary: Datorama Python Package12
Home-page: https://github.com/datorama/python-connector-package
Author: Asaad Awesat
Author-email: asaad.awesat@datorama.com
License: MIT
Platform: UNKNOWN
